ceblpy/__init__.py
ceblpy/ceblpy.py
ceblpy/helpers.py
ceblpy-0.1.1.dist-info/LICENSE
ceblpy-0.1.1.dist-info/METADATA
ceblpy-0.1.1.dist-info/WHEEL
ceblpy-0.1.1.dist-info/RECORD
