Metadata-Version: 2.3
Name: ceblpy
Version: 0.1.1
Summary: Extract and analyze data from the Canadian Elite Basketball league (CEBL).
License: MIT
Author: Ryan Du
Requires-Python: >=3.12,<4.0
Classifier: License :: OSI Approved :: MIT License
Classifier: Programming Language :: Python :: 3
Classifier: Programming Language :: Python :: 3.12
Classifier: Programming Language :: Python :: 3.13
Requires-Dist: pandas (>=2.3.0,<3.0.0)
Project-URL: Documentation, https://ceblpy.readthedocs.io/en/latest/index.html
